.installed.cfg
MANIFEST.in
buildout.cfg
setup.py
src/ice/__init__.py
src/ice.control.egg-info/PKG-INFO
src/ice.control.egg-info/SOURCES.txt
src/ice.control.egg-info/dependency_links.txt
src/ice.control.egg-info/namespace_packages.txt
src/ice.control.egg-info/not-zip-safe
src/ice.control.egg-info/requires.txt
src/ice.control.egg-info/top_level.txt
src/ice/control/__init__.py
src/ice/control/configure.zcml
src/ice/control/browser/__init__.py
src/ice/control/browser/configure.zcml
src/ice/control/browser/control.py
src/ice/control/browser/interfaces.py
src/ice/control/browser/menu.pt
src/ice/control/browser/menu.py
src/ice/control/browser/namespace.py
src/ice/control/controls/__init__.py
src/ice/control/controls/configure.zcml
src/ice/control/controls/details/__init__.py
src/ice/control/controls/details/configure.zcml
src/ice/control/controls/details/base/__init__.py
src/ice/control/controls/details/base/base.pt
src/ice/control/controls/details/base/base.py
src/ice/control/controls/details/base/configure.zcml
src/ice/control/controls/details/configurator/__init__.py
src/ice/control/controls/details/configurator/configurator.pt
src/ice/control/controls/details/configurator/configurator.py
src/ice/control/controls/details/configurator/configure.zcml
src/ice/control/controls/details/contents/__init__.py
src/ice/control/controls/details/contents/configure.zcml
src/ice/control/controls/details/contents/contents.pt
src/ice/control/controls/details/contents/contents.py
src/ice/control/controls/details/dublincore/__init__.py
src/ice/control/controls/details/dublincore/configure.zcml
src/ice/control/controls/details/dublincore/dublincore.pt
src/ice/control/controls/details/dublincore/dublincore.py
src/ice/control/controls/details/error/__init__.py
src/ice/control/controls/details/error/configure.zcml
src/ice/control/controls/details/error/error.pt
src/ice/control/controls/details/error/error.py
src/ice/control/controls/details/error/error_config.pt
src/ice/control/controls/details/error/errorentry.pt
src/ice/control/controls/details/introspector/__init__.py
src/ice/control/controls/details/introspector/configure.zcml
src/ice/control/controls/details/introspector/introspector.pt
src/ice/control/controls/details/localregistry/__init__.py
