Metadata-Version: 1.0
Name: ice.control
Version: 0.3.2
Summary: System Administration and Site Management for BlueBream
Home-page: http://launchpad.net/ice.control
Author: Ilshad R. Khabibullin
Author-email: astoon.net at gmail.com
License: GPL v.3
Platform: UNKNOWN
Classifier: Development Status :: 3 - Alpha
Classifier: Environment :: Web Environment
Classifier: Intended Audience :: Developers
Classifier: Intended Audience :: Customer Service
Classifier: Intended Audience :: System Administrators
Classifier: License :: OSI Approved :: GNU General Public License (GPL)
Classifier: Programming Language :: Python
Classifier: Programming Language :: JavaScript
Classifier: Natural Language :: English
Classifier: Operating System :: OS Independent
Classifier: Topic :: Internet :: WWW/HTTP :: Site Management
Classifier: Framework :: ZODB
Classifier: Framework :: Zope3
